{
    "id": 68654380,
    "name": "Omega Interface",
    "author": "Platnuu",
    "creators": ["Zipixbox","Platnuu"],
    "verifier": "RG",
    "verification": "https://www.youtube.com/watch?v=uCHpKL705DM",
    "percentToQualify": 45,
    "password": "Free To Copy",
    "records": [
        {
            "user": "Lanx",
            "link": "https://www.youtube.com/watch?v=m-m1jdCsJ6s&t=2s",
            "percent": 100,
            "hz": 360
        },
        {
            "user": "Byleom",
            "link": "https://www.youtube.com/watch?v=uCHpKL705DM",
            "percent": 100,
            "hz": 360
        },
        {
            "user": "Dawiderix",
            "link": "https://www.youtube.com/watch?v=wgmIwlKPW7Y",
            "percent": 64,
            "hz": 322
        },
        {
            "user": "MateleQ",
            "link": "https://youtu.be/C_RhUatnJIU?si=yy1thE4CuCTrv5A4",
            "percent": 54,
            "hz": 240
        },
        {
            "user": "default2137",
            "link": "https://www.youtube.com/watch?v=_NekAtLlfZ0",
            "percent": 50,
            "hz": 240
        },
      {
            "user": "nPumpz",
            "link": "https://www.youtube.com/watch?v=C-9fmQXLAPo",
            "percent": 47,
            "hz": 165
        }
    ]
}
