{
    "id": 76865589,
    "name": "Terminux",
    "author": "Rainstorm",
    "creators": ["Rainstorm","ZenthicAlptha","SyQual","iEstia","1374","TheCdPre","VulgarisAerae","Inex","Flosia","Mintjelly"],
    "verifier": "Laniakea",
    "verification": "https://www.youtube.com/watch?v=4bF3RxFBS4k",
    "percentToQualify": 43,
    "password": "271828",
    "records": [
        {
            "user": "UnityHost",
            "link": "https://www.youtube.com/watch?v=4bF3RxFBS4k",
            "percent": 100,
            "hz": 240
        }
    ]
}
